README.txt
setup.py
indianrailways/__init__.py
indianrailways/api.py
indianrailways/cli.py
indianrailways.egg-info/PKG-INFO
indianrailways.egg-info/SOURCES.txt
indianrailways.egg-info/dependency_links.txt
indianrailways.egg-info/entry_points.txt
indianrailways.egg-info/requires.txt
indianrailways.egg-info/top_level.txt