Metadata-Version: 1.0
Name: indianrailways
Version: 0.1
Summary: Python library to interact with Indian Railways website.
Home-page: UNKNOWN
Author: Anand Chitipothu
Author-email: anandology@gmail.com
License: UNKNOWN
Platform: UNKNOWN
